co_words/__init__.py
co_words/sample.py
co_words/utilities.py
co_words/wordcount.py
tests/__init__.py
tests/animal_farm.py
tests/test_utilities.py
tests/test_wordcount.py
o_words-0.0.1.1.dist-info/METADATA
o_words-0.0.1.1.dist-info/WHEEL
o_words-0.0.1.1.dist-info/top_level.txt
o_words-0.0.1.1.dist-info/RECORD
