Metadata-Version: 2.1
Name: o-words
Version: 0.0.1.1
Summary: A python package to complete co-occurring word counts
Home-page: https://github.com/RTIInternational/o-words
Author: Kasey Jones
Author-email: krjones@rti.org
License: UNKNOWN
Platform: UNKNOWN
Classifier: Programming Language :: Python :: 3
Classifier: License :: OSI Approved :: MIT License
Classifier: Operating System :: OS Independent
